Counter12bit.vhd
LIBRARY ieee;
USE ieee.std_logic_1164.ALL;
USE ieee.numeric_std.ALL;
ENTITY counter12bit IS
    PORT (
        clk, reset, en : IN STD_LOGIC;
        n : IN STD_LOGIC_VECTOR(11 DOWNTO 0);
        q : OUT STD_LOGIC_VECTOR(11 DOWNTO 0);
        p : OUT STD_LOGIC);
    -- n is the number that the counter will reset at and pulse at.
    -- p is the pulse output.
END ENTITY;

ARCHITECTURE seq OF counter12bit IS
    SIGNAL r_reg, r_next, r_inc : unsigned(11 DOWNTO 0);
    SIGNAL rollover : BOOLEAN; -- This was originally only intended for player counters; but it's also used for green and red light counter
    SIGNAL p_temp : STD_LOGIC;
BEGIN
    PROCESS (clk, reset, en)
    BEGIN
        IF (reset = '1') THEN
            r_reg <= (OTHERS => '0');
        ELSIF (clk'event AND clk = '1' AND en = '1') THEN
            r_reg <= r_next;
        END IF;
    END PROCESS;
    r_inc <= r_reg + "1";
    r_next <= (OTHERS => '0') WHEN rollover ELSE
              r_inc;
    rollover <= r_inc = UNSIGNED(n);
    q <= STD_LOGIC_VECTOR(r_reg);
    p_temp <= '1' WHEN rollover ELSE '0';
    PROCESS (p_temp, reset)
    BEGIN
        IF (reset = '1') THEN
            p <= '0';
        ELSE
            p <= p_temp;
        END IF;
    END PROCESS;
END ARCHITECTURE;

Counter12bit_testbench.vhd
LIBRARY ieee;
USE ieee.std_logic_1164.ALL;
USE ieee.numeric_std.ALL;
USE ieee.math_real.ALL;
ENTITY Counter12bit_testbench IS
END ENTITY;

ARCHITECTURE rtl OF Counter12bit_testbench IS
    COMPONENT Counter12bit IS
        PORT (
            clk, reset, en : IN STD_LOGIC;
            n : IN STD_LOGIC_VECTOR(11 DOWNTO 0);
            q : OUT STD_LOGIC_VECTOR(11 DOWNTO 0);
            p : OUT STD_LOGIC
        );
    END COMPONENT;
    SIGNAL clk, p : STD_LOGIC := '0';
    SIGNAL reset, en, success : STD_LOGIC := '1';
    SIGNAL n : STD_LOGIC_VECTOR(11 DOWNTO 0) := (OTHERS => '1');
    SIGNAL q : STD_LOGIC_VECTOR(11 DOWNTO 0) := (OTHERS => '0');

BEGIN
    reset <= '1', '0' AFTER 11 ns;
    clk <= NOT clk AFTER 5 ns; --acts as a clock
    dut : Counter12bit
    PORT MAP(
        clk => clk,
        reset => reset,
        en => en,
        n => n,
        q => q,
        p => p
    );
    stimulus :
    PROCESS BEGIN
        WAIT UNTIL reset = '0';
        for i in 0 to 4094 loop
            if q /= STD_LOGIC_VECTOR(to_unsigned(i, q'length)) then
                success <= '0';
            end if;
            if q = "111111111110" then
                if p /= '1' then
                    success <= '0';
                end if;
            end if;
            wait for 10 ns;
        end loop;
        wait;
    END PROCESS stimulus;

END ARCHITECTURE;

Counter12bit_testbench.vcd
$date
  Thu Apr 23 16:05:13 2026
$end
$version
  GHDL v0
$end
$timescale
  1 fs
$end
$scope module standard $end
$upscope $end
$scope module std_logic_1164 $end
$upscope $end
$scope module numeric_std $end
$upscope $end
$scope module math_real $end
$upscope $end
$scope module counter12bit_testbench $end
$var reg 1 ! clk $end
$var reg 1 " p $end
$var reg 1 # reset $end
$var reg 1 $ en $end
$var reg 1 % success $end
$var reg 12 & n[11:0] $end
$var reg 12 ' q[11:0] $end
$scope module dut $end
$var reg 1 ( clk $end
$var reg 1 ) reset $end
$var reg 1 * en $end
$var reg 12 + n[11:0] $end
$var reg 12 , q[11:0] $end
$var reg 1 - p $end
$var reg 12 . r_reg[11:0] $end
$var reg 12 / r_next[11:0] $end
$var reg 12 0 r_inc[11:0] $end
$var reg 1 1 rollover $end
$var reg 1 2 p_temp $end
$upscope $end
$upscope $end
$enddefinitions $end
#0
0!
0"
1#
1$
1%
b111111111111 &
b000000000000 '
0(
1)
1*
b111111111111 +
b000000000000 ,
0-
b000000000000 .
b000000000001 /
b000000000001 0
01
02
#5000000
1!
1(
#10000000
0!
0(
#11000000
0#
0)
#15000000
1!
b000000000001 '
1(
b000000000001 ,
b000000000001 .
b000000000010 /
b000000000010 0
#20000000
0!
0(
#25000000
1!
b000000000010 '
1(
b000000000010 ,
b000000000010 .
b000000000011 /
b000000000011 0
#30000000
0!
0(
#35000000
1!
b000000000011 '
1(
b000000000011 ,
b000000000011 .
b000000000100 /
b000000000100 0
#40000000
0!
0(
#45000000
1!
b000000000100 '
1(
b000000000100 ,
b000000000100 .
b000000000101 /
b000000000101 0
#50000000
0!
0(
#55000000
1!
b000000000101 '
1(
b000000000101 ,
b000000000101 .
b000000000110 /
b000000000110 0
#60000000
0!
0(
#65000000
1!
b000000000110 '
1(
b000000000110 ,
b000000000110 .
b000000000111 /
b000000000111 0
#70000000
0!
0(
#75000000
1!
b000000000111 '
1(
b000000000111 ,
b000000000111 .
b000000001000 /
b000000001000 0
#80000000
0!
0(
#85000000
1!
b000000001000 '
1(
b000000001000 ,
b000000001000 .
b000000001001 /
b000000001001 0
#90000000
0!
0(
#95000000
1!
b000000001001 '
1(
b000000001001 ,
b000000001001 .
b000000001010 /
b000000001010 0
#100000000
0!
0(
#105000000
1!
b000000001010 '
1(
b000000001010 ,
b000000001010 .
b000000001011 /
b000000001011 0
#110000000
0!
0(
#115000000
1!
b000000001011 '
1(
b000000001011 ,
b000000001011 .
b000000001100 /
b000000001100 0
#120000000
0!
0(
#125000000
1!
b000000001100 '
1(
b000000001100 ,
b000000001100 .
b000000001101 /
b000000001101 0
#130000000
0!
0(
#135000000
1!
b000000001101 '
1(
b000000001101 ,
b000000001101 .
b000000001110 /
b000000001110 0
#140000000
0!
0(
#145000000
1!
b000000001110 '
1(
b000000001110 ,
b000000001110 .
b000000001111 /
b000000001111 0
#150000000
0!
0(
#155000000
1!
b000000001111 '
1(
b000000001111 ,
b000000001111 .
b000000010000 /
b000000010000 0
#160000000
0!
0(
#165000000
1!
b000000010000 '
1(
b000000010000 ,
b000000010000 .
b000000010001 /
b000000010001 0
#170000000
0!
0(
#175000000
1!
b000000010001 '
1(
b000000010001 ,
b000000010001 .
b000000010010 /
b000000010010 0
#180000000
0!
0(
#185000000
1!
b000000010010 '
1(
b000000010010 ,
b000000010010 .
b000000010011 /
b000000010011 0
#190000000
0!
0(
#195000000
1!
b000000010011 '
1(
b000000010011 ,
b000000010011 .
b000000010100 /
b000000010100 0
#200000000
0!
0(
#205000000
1!
b000000010100 '
1(
b000000010100 ,
b000000010100 .
b000000010101 /
b000000010101 0
#210000000
0!
0(
#215000000
1!
b000000010101 '
1(
b000000010101 ,
b000000010101 .
b000000010110 /
b000000010110 0
#220000000
0!
0(
#225000000
1!
b000000010110 '
1(
b000000010110 ,
b000000010110 .
b000000010111 /
b000000010111 0
#230000000
0!
0(
#235000000
1!
b000000010111 '
1(
b000000010111 ,
b000000010111 .
b000000011000 /
b000000011000 0
#240000000
0!
0(
#245000000
1!
b000000011000 '
1(
b000000011000 ,
b000000011000 .
b000000011001 /
b000000011001 0
#250000000
0!
0(
#255000000
1!
b000000011001 '
1(
b000000011001 ,
b000000011001 .
b000000011010 /
b000000011010 0
#260000000
0!
0(
#265000000
1!
b000000011010 '
1(
b000000011010 ,
b000000011010 .
b000000011011 /
b000000011011 0
#270000000
0!
0(
#275000000
1!
b000000011011 '
1(
b000000011011 ,
b000000011011 .
b000000011100 /
b000000011100 0
#280000000
0!
0(
#285000000
1!
b000000011100 '
1(
b000000011100 ,
b000000011100 .
b000000011101 /
b000000011101 0
#290000000
0!
0(
#295000000
1!
b000000011101 '
1(
b000000011101 ,
b000000011101 .
b000000011110 /
b000000011110 0
#300000000
0!
0(
#305000000
1!
b000000011110 '
1(
b000000011110 ,
b000000011110 .
b000000011111 /
b000000011111 0
#310000000
0!
0(
#315000000
1!
b000000011111 '
1(
b000000011111 ,
b000000011111 .
b000000100000 /
b000000100000 0
#320000000
0!
0(
#325000000
1!
b000000100000 '
1(
b000000100000 ,
b000000100000 .
b000000100001 /
b000000100001 0
#330000000
0!
0(
#335000000
1!
b000000100001 '
1(
b000000100001 ,
b000000100001 .
b000000100010 /
b000000100010 0
#340000000
0!
0(
#345000000
1!
b000000100010 '
1(
b000000100010 ,
b000000100010 .
b000000100011 /
b000000100011 0
#350000000
0!
0(
#355000000
1!
b000000100011 '
1(
b000000100011 ,
b000000100011 .
b000000100100 /
b000000100100 0
#360000000
0!
0(
#365000000
1!
b000000100100 '
1(
b000000100100 ,
b000000100100 .
b000000100101 /
b000000100101 0
#370000000
0!
0(
#375000000
1!
b000000100101 '
1(
b000000100101 ,
b000000100101 .
b000000100110 /
b000000100110 0
#380000000
0!
0(
#385000000
1!
b000000100110 '
1(
b000000100110 ,
b000000100110 .
b000000100111 /
b000000100111 0
#390000000
0!
0(
#395000000
1!
b000000100111 '
1(
b000000100111 ,
b000000100111 .
b000000101000 /
b000000101000 0
#400000000
0!
0(
#405000000
1!
b000000101000 '
1(
b000000101000 ,
b000000101000 .
b000000101001 /
b000000101001 0
#410000000
0!
0(
#415000000
1!
b000000101001 '
1(
b000000101001 ,
b000000101001 .
b000000101010 /
b000000101010 0
#420000000
0!
0(
#425000000
1!
b000000101010 '
1(
b000000101010 ,
b000000101010 .
b000000101011 /
b000000101011 0
#430000000
0!
0(
#435000000
1!
b000000101011 '
1(
b000000101011 ,
b000000101011 .
b000000101100 /
b000000101100 0
#440000000
0!
0(
#445000000
1!
b000000101100 '
1(
b000000101100 ,
b000000101100 .
b000000101101 /
b000000101101 0
#450000000
0!
0(
#455000000
1!
b000000101101 '
1(
b000000101101 ,
b000000101101 .
b000000101110 /
b000000101110 0
#460000000
0!
0(
#465000000
1!
b000000101110 '
1(
b000000101110 ,
b000000101110 .
b000000101111 /
b000000101111 0
#470000000
0!
0(
#475000000
1!
b000000101111 '
1(
b000000101111 ,
b000000101111 .
b000000110000 /
b000000110000 0
#480000000
0!
0(
#485000000
1!
b000000110000 '
1(
b000000110000 ,
b000000110000 .
b000000110001 /
b000000110001 0
#490000000
0!
0(
#495000000
1!
b000000110001 '
1(
b000000110001 ,
b000000110001 .
b000000110010 /
b000000110010 0
#500000000
0!
0(
#505000000
1!
b000000110010 '
1(
b000000110010 ,
b000000110010 .
b000000110011 /
b000000110011 0
#510000000
0!
0(
#515000000
1!
b000000110011 '
1(
b000000110011 ,
b000000110011 .
b000000110100 /
b000000110100 0
#520000000
0!
0(
#525000000
1!
b000000110100 '
1(
b000000110100 ,
b000000110100 .
b000000110101 /
b000000110101 0
#530000000
0!
0(
#535000000
1!
b000000110101 '
1(
b000000110101 ,
b000000110101 .
b000000110110 /
b000000110110 0
#540000000
0!
0(
#545000000
1!
b000000110110 '
1(
b000000110110 ,
b000000110110 .
b000000110111 /
b000000110111 0
#550000000
0!
0(
#555000000
1!
b000000110111 '
1(
b000000110111 ,
b000000110111 .
b000000111000 /
b000000111000 0
#560000000
0!
0(
#565000000
1!
b000000111000 '
1(
b000000111000 ,
b000000111000 .
b000000111001 /
b000000111001 0
#570000000
0!
0(
#575000000
1!
b000000111001 '
1(
b000000111001 ,
b000000111001 .
b000000111010 /
b000000111010 0
#580000000
0!
0(
#585000000
1!
b000000111010 '
1(
b000000111010 ,
b000000111010 .
b000000111011 /
b000000111011 0
#590000000
0!
0(
#595000000
1!
b000000111011 '
1(
b000000111011 ,
b000000111011 .
b000000111100 /
b000000111100 0
#600000000
0!
0(
#605000000
1!
b000000111100 '
1(
b000000111100 ,
b000000111100 .
b000000111101 /
b000000111101 0
#610000000
0!
0(
#615000000
1!
b000000111101 '
1(
b000000111101 ,
b000000111101 .
b000000111110 /
b000000111110 0
#620000000
0!
0(
#625000000
1!
b000000111110 '
1(
b000000111110 ,
b000000111110 .
b000000111111 /
b000000111111 0
#630000000
0!
0(
#635000000
1!
b000000111111 '
1(
b000000111111 ,
b000000111111 .
b000001000000 /
b000001000000 0
#640000000
0!
0(
#645000000
1!
b000001000000 '
1(
b000001000000 ,
b000001000000 .
b000001000001 /
b000001000001 0
#650000000
0!
0(
#655000000
1!
b000001000001 '
1(
b000001000001 ,
b000001000001 .
b000001000010 /
b000001000010 0
#660000000
0!
0(
#665000000
1!
b000001000010 '
1(
b000001000010 ,
b000001000010 .
b000001000011 /
b000001000011 0
#670000000
0!
0(
#675000000
1!
b000001000011 '
1(
b000001000011 ,
b000001000011 .
b000001000100 /
b000001000100 0
#680000000
0!
0(
#685000000
1!
b000001000100 '
1(
b000001000100 ,
b000001000100 .
b000001000101 /
b000001000101 0
#690000000
0!
0(
#695000000
1!
b000001000101 '
1(
b000001000101 ,
b000001000101 .
b000001000110 /
b000001000110 0
#700000000
0!
0(
#705000000
1!
b000001000110 '
1(
b000001000110 ,
b000001000110 .
b000001000111 /
b000001000111 0
#710000000
0!
0(
#715000000
1!
b000001000111 '
1(
b000001000111 ,
b000001000111 .
b000001001000 /
b000001001000 0
#720000000
0!
0(
#725000000
1!
b000001001000 '
1(
b000001001000 ,
b000001001000 .
b000001001001 /
b000001001001 0
#730000000
0!
0(
#735000000
1!
b000001001001 '
1(
b000001001001 ,
b000001001001 .
b000001001010 /
b000001001010 0
#740000000
0!
0(
#745000000
1!
b000001001010 '
1(
b000001001010 ,
b000001001010 .
b000001001011 /
b000001001011 0
#750000000
0!
0(
#755000000
1!
b000001001011 '
1(
b000001001011 ,
b000001001011 .
b000001001100 /
b000001001100 0
#760000000
0!
0(
#765000000
1!
b000001001100 '
1(
b000001001100 ,
b000001001100 .
b000001001101 /
b000001001101 0
#770000000
0!
0(
#775000000
1!
b000001001101 '
1(
b000001001101 ,
b000001001101 .
b000001001110 /
b000001001110 0
#780000000
0!
0(
#785000000
1!
b000001001110 '
1(
b000001001110 ,
b000001001110 .
b000001001111 /
b000001001111 0
#790000000
0!
0(
#795000000
1!
b000001001111 '
1(
b000001001111 ,
b000001001111 .
b000001010000 /
b000001010000 0
#800000000
0!
0(
#805000000
1!
b000001010000 '
1(
b000001010000 ,
b000001010000 .
b000001010001 /
b000001010001 0
#810000000
0!
0(
#815000000
1!
b000001010001 '
1(
b000001010001 ,
b000001010001 .
b000001010010 /
b000001010010 0
#820000000
0!
0(
#825000000
1!
b000001010010 '
1(
b000001010010 ,
b000001010010 .
b000001010011 /
b000001010011 0
#830000000
0!
0(
#835000000
1!
b000001010011 '
1(
b000001010011 ,
b000001010011 .
b000001010100 /
b000001010100 0
#840000000
0!
0(
#845000000
1!
b000001010100 '
1(
b000001010100 ,
b000001010100 .
b000001010101 /
b000001010101 0
#850000000
0!
0(
#855000000
1!
b000001010101 '
1(
b000001010101 ,
b000001010101 .
b000001010110 /
b000001010110 0
#860000000
0!
0(
#865000000
1!
b000001010110 '
1(
b000001010110 ,
b000001010110 .
b000001010111 /
b000001010111 0
#870000000
0!
0(
#875000000
1!
b000001010111 '
1(
b000001010111 ,
b000001010111 .
b000001011000 /
b000001011000 0
#880000000
0!
0(
#885000000
1!
b000001011000 '
1(
b000001011000 ,
b000001011000 .
b000001011001 /
b000001011001 0
#890000000
0!
0(
#895000000
1!
b000001011001 '
1(
b000001011001 ,
b000001011001 .
b000001011010 /
b000001011010 0
#900000000
0!
0(
#905000000
1!
b000001011010 '
1(
b000001011010 ,
b000001011010 .
b000001011011 /
b000001011011 0
#910000000
0!
0(
#915000000
1!
b000001011011 '
1(
b000001011011 ,
b000001011011 .
b000001011100 /
b000001011100 0
#920000000
0!
0(
#925000000
1!
b000001011100 '
1(
b000001011100 ,
b000001011100 .
b000001011101 /
b000001011101 0
#930000000
0!
0(
#935000000
1!
b000001011101 '
1(
b000001011101 ,
b000001011101 .
b000001011110 /
b000001011110 0
#940000000
0!
0(
#945000000
1!
b000001011110 '
1(
b000001011110 ,
b000001011110 .
b000001011111 /
b000001011111 0
#950000000
0!
0(
#955000000
1!
b000001011111 '
1(
b000001011111 ,
b000001011111 .
b000001100000 /
b000001100000 0
#960000000
0!
0(
#965000000
1!
b000001100000 '
1(
b000001100000 ,
b000001100000 .
b000001100001 /
b000001100001 0
#970000000
0!
0(
#975000000
1!
b000001100001 '
1(
b000001100001 ,
b000001100001 .
b000001100010 /
b000001100010 0
#980000000
0!
0(
#985000000
1!
b000001100010 '
1(
b000001100010 ,
b000001100010 .
b000001100011 /
b000001100011 0
#990000000
0!
0(
#995000000
1!
b000001100011 '
1(
b000001100011 ,
b000001100011 .
b000001100100 /
b000001100100 0
#1000000000
0!
0(
#1005000000
1!
b000001100100 '
1(
b000001100100 ,
b000001100100 .
b000001100101 /
b000001100101 0
#1010000000
0!
0(
#1015000000
1!
b000001100101 '
1(
b000001100101 ,
b000001100101 .
b000001100110 /
b000001100110 0
#1020000000
0!
0(
#1025000000
1!
b000001100110 '
1(
b000001100110 ,
b000001100110 .
b000001100111 /
b000001100111 0
#1030000000
0!
0(
#1035000000
1!
b000001100111 '
1(
b000001100111 ,
b000001100111 .
b000001101000 /
b000001101000 0
#1040000000
0!
0(
#1045000000
1!
b000001101000 '
1(
b000001101000 ,
b000001101000 .
b000001101001 /
b000001101001 0
#1050000000
0!
0(
#1055000000
1!
b000001101001 '
1(
b000001101001 ,
b000001101001 .
b000001101010 /
b000001101010 0
#1060000000
0!
0(
#1065000000
1!
b000001101010 '
1(
b000001101010 ,
b000001101010 .
b000001101011 /
b000001101011 0
#1070000000
0!
0(
#1075000000
1!
b000001101011 '
1(
b000001101011 ,
b000001101011 .
b000001101100 /
b000001101100 0
#1080000000
0!
0(
#1085000000
1!
b000001101100 '
1(
b000001101100 ,
b000001101100 .
b000001101101 /
b000001101101 0
#1090000000
0!
0(
#1095000000
1!
b000001101101 '
1(
b000001101101 ,
b000001101101 .
b000001101110 /
b000001101110 0
#1100000000
0!
0(
#1105000000
1!
b000001101110 '
1(
b000001101110 ,
b000001101110 .
b000001101111 /
b000001101111 0
#1110000000
0!
0(
#1115000000
1!
b000001101111 '
1(
b000001101111 ,
b000001101111 .
b000001110000 /
b000001110000 0
#1120000000
0!
0(
#1125000000
1!
b000001110000 '
1(
b000001110000 ,
b000001110000 .
b000001110001 /
b000001110001 0
#1130000000
0!
0(
#1135000000
1!
b000001110001 '
1(
b000001110001 ,
b000001110001 .
b000001110010 /
b000001110010 0
#1140000000
0!
0(
#1145000000
1!
b000001110010 '
1(
b000001110010 ,
b000001110010 .
b000001110011 /
b000001110011 0
#1150000000
0!
0(
#1155000000
1!
b000001110011 '
1(
b000001110011 ,
b000001110011 .
b000001110100 /
b000001110100 0
#1160000000
0!
0(
#1165000000
1!
b000001110100 '
1(
b000001110100 ,
b000001110100 .
b000001110101 /
b000001110101 0
#1170000000
0!
0(
#1175000000
1!
b000001110101 '
1(
b000001110101 ,
b000001110101 .
b000001110110 /
b000001110110 0
#1180000000
0!
0(
#1185000000
1!
b000001110110 '
1(
b000001110110 ,
b000001110110 .
b000001110111 /
b000001110111 0
#1190000000
0!
0(
#1195000000
1!
b000001110111 '
1(
b000001110111 ,
b000001110111 .
b000001111000 /
b000001111000 0
#1200000000
0!
0(
#1205000000
1!
b000001111000 '
1(
b000001111000 ,
b000001111000 .
b000001111001 /
b000001111001 0
#1210000000
0!
0(
#1215000000
1!
b000001111001 '
1(
b000001111001 ,
b000001111001 .
b000001111010 /
b000001111010 0
#1220000000
0!
0(
#1225000000
1!
b000001111010 '
1(
b000001111010 ,
b000001111010 .
b000001111011 /
b000001111011 0
#1230000000
0!
0(
#1235000000
1!
b000001111011 '
1(
b000001111011 ,
b000001111011 .
b000001111100 /
b000001111100 0
#1240000000
0!
0(
#1245000000
1!
b000001111100 '
1(
b000001111100 ,
b000001111100 .
b000001111101 /
b000001111101 0
#1250000000
0!
0(
#1255000000
1!
b000001111101 '
1(
b000001111101 ,
b000001111101 .
b000001111110 /
b000001111110 0
#1260000000
0!
0(
#1265000000
1!
b000001111110 '
1(
b000001111110 ,
b000001111110 .
b000001111111 /
b000001111111 0
#1270000000
0!
0(
#1275000000
1!
b000001111111 '
1(
b000001111111 ,
b000001111111 .
b000010000000 /
b000010000000 0
#1280000000
0!
0(
#1285000000
1!
b000010000000 '
1(
b000010000000 ,
b000010000000 .
b000010000001 /
b000010000001 0
#1290000000
0!
0(
#1295000000
1!
b000010000001 '
1(
b000010000001 ,
b000010000001 .
b000010000010 /
b000010000010 0
#1300000000
0!
0(
#1305000000
1!
b000010000010 '
1(
b000010000010 ,
b000010000010 .
b000010000011 /
b000010000011 0
#1310000000
0!
0(
#1315000000
1!
b000010000011 '
1(
b000010000011 ,
b000010000011 .
b000010000100 /
b000010000100 0
#1320000000
0!
0(
#1325000000
1!
b000010000100 '
1(
b000010000100 ,
b000010000100 .
b000010000101 /
b000010000101 0
#1330000000
0!
0(
#1335000000
1!
b000010000101 '
1(
b000010000101 ,
b000010000101 .
b000010000110 /
b000010000110 0
#1340000000
0!
0(
#1345000000
1!
b000010000110 '
1(
b000010000110 ,
b000010000110 .
b000010000111 /
b000010000111 0
#1350000000
0!
0(
#1355000000
1!
b000010000111 '
1(
b000010000111 ,
b000010000111 .
b000010001000 /
b000010001000 0
#1360000000
0!
0(
#1365000000
1!
b000010001000 '
1(
b000010001000 ,
b000010001000 .
b000010001001 /
b000010001001 0
#1370000000
0!
0(
#1375000000
1!
b000010001001 '
1(
b000010001001 ,
b000010001001 .
b000010001010 /
b000010001010 0
#1380000000
0!
0(
#1385000000
1!
b000010001010 '
1(
b000010001010 ,
b000010001010 .
b000010001011 /
b000010001011 0
#1390000000
0!
0(
#1395000000
1!
b000010001011 '
1(
b000010001011 ,
b000010001011 .
b000010001100 /
b000010001100 0
#1400000000
0!
0(
#1405000000
1!
b000010001100 '
1(
b000010001100 ,
b000010001100 .
b000010001101 /
b000010001101 0
#1410000000
0!
0(
#1415000000
1!
b000010001101 '
1(
b000010001101 ,
b000010001101 .
b000010001110 /
b000010001110 0
#1420000000
0!
0(
#1425000000
1!
b000010001110 '
1(
b000010001110 ,
b000010001110 .
b000010001111 /
b000010001111 0
#1430000000
0!
0(
#1435000000
1!
b000010001111 '
1(
b000010001111 ,
b000010001111 .
b000010010000 /
b000010010000 0
#1440000000
0!
0(
#1445000000
1!
b000010010000 '
1(
b000010010000 ,
b000010010000 .
b000010010001 /
b000010010001 0
#1450000000
0!
0(
#1455000000
1!
b000010010001 '
1(
b000010010001 ,
b000010010001 .
b000010010010 /
b000010010010 0
#1460000000
0!
0(
#1465000000
1!
b000010010010 '
1(
b000010010010 ,
b000010010010 .
b000010010011 /
b000010010011 0
#1470000000
0!
0(
#1475000000
1!
b000010010011 '
1(
b000010010011 ,
b000010010011 .
b000010010100 /
b000010010100 0
#1480000000
0!
0(
#1485000000
1!
b000010010100 '
1(
b000010010100 ,
b000010010100 .
b000010010101 /
b000010010101 0
#1490000000
0!
0(
#1495000000
1!
b000010010101 '
1(
b000010010101 ,
b000010010101 .
b000010010110 /
b000010010110 0
#1500000000
0!
0(
#1505000000
1!
b000010010110 '
1(
b000010010110 ,
b000010010110 .
b000010010111 /
b000010010111 0
#1510000000
0!
0(
#1515000000
1!
b000010010111 '
1(
b000010010111 ,
b000010010111 .
b000010011000 /
b000010011000 0
#1520000000
0!
0(
#1525000000
1!
b000010011000 '
1(
b000010011000 ,
b000010011000 .
b000010011001 /
b000010011001 0
#1530000000
0!
0(
#1535000000
1!
b000010011001 '
1(
b000010011001 ,
b000010011001 .
b000010011010 /
b000010011010 0
#1540000000
0!
0(
#1545000000
1!
b000010011010 '
1(
b000010011010 ,
b000010011010 .
b000010011011 /
b000010011011 0
#1550000000
0!
0(
#1555000000
1!
b000010011011 '
1(
b000010011011 ,
b000010011011 .
b000010011100 /
b000010011100 0
#1560000000
0!
0(
#1565000000
1!
b000010011100 '
1(
b000010011100 ,
b000010011100 .
b000010011101 /
b000010011101 0
#1570000000
0!
0(
#1575000000
1!
b000010011101 '
1(
b000010011101 ,
b000010011101 .
b000010011110 /
b000010011110 0
#1580000000
0!
0(
#1585000000
1!
b000010011110 '
1(
b000010011110 ,
b000010011110 .
b000010011111 /
b000010011111 0
#1590000000
0!
0(
#1595000000
1!
b000010011111 '
1(
b000010011111 ,
b000010011111 .
b000010100000 /
b000010100000 0
#1600000000
0!
0(
#1605000000
1!
b000010100000 '
1(
b000010100000 ,
b000010100000 .
b000010100001 /
b000010100001 0
#1610000000
0!
0(
#1615000000
1!
b000010100001 '
1(
b000010100001 ,
b000010100001 .
b000010100010 /
b000010100010 0
#1620000000
0!
0(
#1625000000
1!
b000010100010 '
1(
b000010100010 ,
b000010100010 .
b000010100011 /
b000010100011 0
#1630000000
0!
0(
#1635000000
1!
b000010100011 '
1(
b000010100011 ,
b000010100011 .
b000010100100 /
b000010100100 0
#1640000000
0!
0(
#1645000000
1!
b000010100100 '
1(
b000010100100 ,
b000010100100 .
b000010100101 /
b000010100101 0
#1650000000
0!
0(
#1655000000
1!
b000010100101 '
1(
b000010100101 ,
b000010100101 .
b000010100110 /
b000010100110 0
#1660000000
0!
0(
#1665000000
1!
b000010100110 '
1(
b000010100110 ,
b000010100110 .
b000010100111 /
b000010100111 0
#1670000000
0!
0(
#1675000000
1!
b000010100111 '
1(
b000010100111 ,
b000010100111 .
b000010101000 /
b000010101000 0
#1680000000
0!
0(
#1685000000
1!
b000010101000 '
1(
b000010101000 ,
b000010101000 .
b000010101001 /
b000010101001 0
#1690000000
0!
0(
#1695000000
1!
b000010101001 '
1(
b000010101001 ,
b000010101001 .
b000010101010 /
b000010101010 0
#1700000000
0!
0(
#1705000000
1!
b000010101010 '
1(
b000010101010 ,
b000010101010 .
b000010101011 /
b000010101011 0
#1710000000
0!
0(
#1715000000
1!
b000010101011 '
1(
b000010101011 ,
b000010101011 .
b000010101100 /
b000010101100 0
#1720000000
0!
0(
#1725000000
1!
b000010101100 '
1(
b000010101100 ,
b000010101100 .
b000010101101 /
b000010101101 0
#1730000000
0!
0(
#1735000000
1!
b000010101101 '
1(
b000010101101 ,
b000010101101 .
b000010101110 /
b000010101110 0
#1740000000
0!
0(
#1745000000
1!
b000010101110 '
1(
b000010101110 ,
b000010101110 .
b000010101111 /
b000010101111 0
#1750000000
0!
0(
#1755000000
1!
b000010101111 '
1(
b000010101111 ,
b000010101111 .
b000010110000 /
b000010110000 0
#1760000000
0!
0(
#1765000000
1!
b000010110000 '
1(
b000010110000 ,
b000010110000 .
b000010110001 /
b000010110001 0
#1770000000
0!
0(
#1775000000
1!
b000010110001 '
1(
b000010110001 ,
b000010110001 .
b000010110010 /
b000010110010 0
#1780000000
0!
0(
#1785000000
1!
b000010110010 '
1(
b000010110010 ,
b000010110010 .
b000010110011 /
b000010110011 0
#1790000000
0!
0(
#1795000000
1!
b000010110011 '
1(
b000010110011 ,
b000010110011 .
b000010110100 /
b000010110100 0
#1800000000
0!
0(
#1805000000
1!
b000010110100 '
1(
b000010110100 ,
b000010110100 .
b000010110101 /
b000010110101 0
#1810000000
0!
0(
#1815000000
1!
b000010110101 '
1(
b000010110101 ,
b000010110101 .
b000010110110 /
b000010110110 0
#1820000000
0!
0(
#1825000000
1!
b000010110110 '
1(
b000010110110 ,
b000010110110 .
b000010110111 /
b000010110111 0
#1830000000
0!
0(
#1835000000
1!
b000010110111 '
1(
b000010110111 ,
b000010110111 .
b000010111000 /
b000010111000 0
#1840000000
0!
0(
#1845000000
1!
b000010111000 '
1(
b000010111000 ,
b000010111000 .
b000010111001 /
b000010111001 0
#1850000000
0!
0(
#1855000000
1!
b000010111001 '
1(
b000010111001 ,
b000010111001 .
b000010111010 /
b000010111010 0
#1860000000
0!
0(
#1865000000
1!
b000010111010 '
1(
b000010111010 ,
b000010111010 .
b000010111011 /
b000010111011 0
#1870000000
0!
0(
#1875000000
1!
b000010111011 '
1(
b000010111011 ,
b000010111011 .
b000010111100 /
b000010111100 0
#1880000000
0!
0(
#1885000000
1!
b000010111100 '
1(
b000010111100 ,
b000010111100 .
b000010111101 /
b000010111101 0
#1890000000
0!
0(
#1895000000
1!
b000010111101 '
1(
b000010111101 ,
b000010111101 .
b000010111110 /
b000010111110 0
#1900000000
0!
0(
#1905000000
1!
b000010111110 '
1(
b000010111110 ,
b000010111110 .
b000010111111 /
b000010111111 0
#1910000000
0!
0(
#1915000000
1!
b000010111111 '
1(
b000010111111 ,
b000010111111 .
b000011000000 /
b000011000000 0
#1920000000
0!
0(
#1925000000
1!
b000011000000 '
1(
b000011000000 ,
b000011000000 .
b000011000001 /
b000011000001 0
#1930000000
0!
0(
#1935000000
1!
b000011000001 '
1(
b000011000001 ,
b000011000001 .
b000011000010 /
b000011000010 0
#1940000000
0!
0(
#1945000000
1!
b000011000010 '
1(
b000011000010 ,
b000011000010 .
b000011000011 /
b000011000011 0
#1950000000
0!
0(
#1955000000
1!
b000011000011 '
1(
b000011000011 ,
b000011000011 .
b000011000100 /
b000011000100 0
#1960000000
0!
0(
#1965000000
1!
b000011000100 '
1(
b000011000100 ,
b000011000100 .
b000011000101 /
b000011000101 0
#1970000000
0!
0(
#1975000000
1!
b000011000101 '
1(
b000011000101 ,
b000011000101 .
b000011000110 /
b000011000110 0
#1980000000
0!
0(
#1985000000
1!
b000011000110 '
1(
b000011000110 ,
b000011000110 .
b000011000111 /
b000011000111 0
#1990000000
0!
0(
#1995000000
1!
b000011000111 '
1(
b000011000111 ,
b000011000111 .
b000011001000 /
b000011001000 0
#2000000000
0!
0(
#2005000000
1!
b000011001000 '
1(
b000011001000 ,
b000011001000 .
b000011001001 /
b000011001001 0
#2010000000
0!
0(
#2015000000
1!
b000011001001 '
1(
b000011001001 ,
b000011001001 .
b000011001010 /
b000011001010 0
#2020000000
0!
0(
#2025000000
1!
b000011001010 '
1(
b000011001010 ,
b000011001010 .
b000011001011 /
b000011001011 0
#2030000000
0!
0(
#2035000000
1!
b000011001011 '
1(
b000011001011 ,
b000011001011 .
b000011001100 /
b000011001100 0
#2040000000
0!
0(
