Counter4bit.vhd
LIBRARY ieee;
USE ieee.std_logic_1164.ALL;
USE ieee.numeric_std.ALL;
ENTITY counter4bit IS
    PORT (
        reset, clk, en : IN STD_LOGIC;
        n : IN STD_LOGIC_VECTOR(3 DOWNTO 0);
        q : OUT STD_LOGIC_VECTOR(3 DOWNTO 0);
        p : OUT STD_LOGIC);
    -- n is the number that the counter will reset at and pulse at.
END ENTITY;

ARCHITECTURE seq OF counter4bit IS
    SIGNAL r_reg, r_next, r_inc : unsigned(3 DOWNTO 0) := (others => '0');
    SIGNAL rollover : BOOLEAN;
BEGIN
    PROCESS (clk, reset, en)
    BEGIN
        IF (reset = '1') THEN
            r_reg <= (OTHERS => '0');
        ELSIF rising_edge(clk) AND en = '1' THEN
            r_reg <= r_next;
        END IF;
    END PROCESS;
    r_inc <= r_reg + "1";
    r_next <= (OTHERS => '0') WHEN rollover ELSE
              r_inc;
    rollover <= r_inc = unsigned(n);
    q <= STD_LOGIC_VECTOR(r_reg);
    p <= '1' WHEN rollover ELSE '0';
    --        PROCESS (rollover, reset)
    --        BEGIN
    --            IF (reset = '1') THEN
    --                p <= '0';
    --            ELSIF rollover THEN
    --                p <= '1';
    --            END IF;
    --        END PROCESS;
END ARCHITECTURE;

Counter4bitTestbench.vhd
library ieee;
use ieee.std_logic_1164.all;
use ieee.numeric_std.all;
use ieee.math_real.all;
entity Counter4bitTestbench is
end Counter4bitTestbench;

architecture arch of Counter4bitTestbench is
    component Counter4bit is
        port (
            reset, clk, en : IN STD_LOGIC;
            n : IN STD_LOGIC_VECTOR(3 DOWNTO 0);
            q : OUT STD_LOGIC_VECTOR(3 DOWNTO 0);
            p : OUT STD_LOGIC
        );
    end component;
    signal clk : STD_LOGIC := '0';
    signal n : STD_LOGIC_VECTOR(3 DOWNTO 0) := "1111";
    signal q : STD_LOGIC_VECTOR(3 DOWNTO 0) := "0000";
    signal p : STD_LOGIC := '0';
    signal reset, success, en : std_logic := '1';
begin
    reset <= '1', '0' after 11 ns;
    clk <= not clk after 5 ns; --acts as a clock
    dut:counter4bit
    port map(
        reset => reset,
        clk => clk,
        n => n,
        q => q,
        p => p,
        en => en
    );
    stimulus:
    process begin
        wait until reset = '0';
        wait for 5 ns;
        if q /= "0001" then
            success <= '0';
        end if;
        wait for 10 ns;
        if q /= "0010" then
            success <= '0';
        end if;
        wait for 10 ns;
        if q /= "0011" then
            success <= '0';
        end if;
        wait for 10 ns;
        if q /= "0100" then
            success <= '0';
        end if;
        wait for 10 ns;
        if q /= "0101" then
            success <= '0';
        end if;
        wait for 10 ns;
        if q /= "0110" then
            success <= '0';
        end if;
        wait for 10 ns;
        if q /= "0111" then
            success <= '0';
        end if;
        wait for 10 ns;
        if q /= "1000" then
            success <= '0';
        end if;
        wait for 10 ns;
        if q /= "1001" then
            success <= '0';
        end if;
        wait for 10 ns;
        if q /= "1010" then
            success <= '0';
        end if;
        wait for 10 ns;
        if q /= "1011" then
            success <= '0';
        end if;
        wait for 10 ns;
        if q /= "1100" then
            success <= '0';
        end if;
        wait for 10 ns;
        if q /= "1101" then
            success <= '0';
        end if;
        wait for 10 ns;
        if (q /= "1110") and (p = '1') then
            success <= '0';
        end if;
        wait for 10 ns;
        if q /= "0000" then
            success <= '0';
        end if;
        n <= "1110";
        wait for 140 ns;
        if q /= "0000" then
            success <= '0';
        end if;
        n <= "1000";
        wait for 80 ns;
        if q /= "0000" then
            success <= '0';
        end if;
        wait for 16 ns;
        en <= '0';
        wait for 10 ns;
        if q /= "0001" then
            success <= '0';
        end if;
        wait;
    end process stimulus;
end arch;

Counter4bitTestbench.vcd
$date
  Thu Apr 23 16:00:20 2026
$end
$version
  GHDL v0
$end
$timescale
  1 fs
$end
$scope module standard $end
$upscope $end
$scope module std_logic_1164 $end
$upscope $end
$scope module numeric_std $end
$upscope $end
$scope module math_real $end
$upscope $end
$scope module counter4bittestbench $end
$var reg 1 ! clk $end
$var reg 4 " n[3:0] $end
$var reg 4 # q[3:0] $end
$var reg 1 $ p $end
$var reg 1 % reset $end
$var reg 1 & success $end
$var reg 1 ' en $end
$scope module dut $end
$var reg 1 ( reset $end
$var reg 1 ) clk $end
$var reg 1 * en $end
$var reg 4 + n[3:0] $end
$var reg 4 , q[3:0] $end
$var reg 1 - p $end
$var reg 4 . r_reg[3:0] $end
$var reg 4 / r_next[3:0] $end
$var reg 4 0 r_inc[3:0] $end
$var reg 1 1 rollover $end
$upscope $end
$upscope $end
$enddefinitions $end
#0
0!
b1111 "
b0000 #
0$
1%
1&
1'
1(
0)
1*
b1111 +
b0000 ,
0-
b0000 .
b0001 /
b0001 0
01
#5000000
1!
1)
#10000000
0!
0)
#11000000
0%
0(
#15000000
1!
b0001 #
1)
b0001 ,
b0001 .
b0010 /
b0010 0
#20000000
0!
0)
#25000000
1!
b0010 #
1)
b0010 ,
b0010 .
b0011 /
b0011 0
#30000000
0!
0)
#35000000
1!
b0011 #
1)
b0011 ,
b0011 .
b0100 /
b0100 0
#40000000
0!
0)
#45000000
1!
b0100 #
1)
b0100 ,
b0100 .
b0101 /
b0101 0
#50000000
0!
0)
#55000000
1!
b0101 #
1)
b0101 ,
b0101 .
b0110 /
b0110 0
#60000000
0!
0)
#65000000
1!
b0110 #
1)
b0110 ,
b0110 .
b0111 /
b0111 0
#70000000
0!
0)
#75000000
1!
b0111 #
1)
b0111 ,
b0111 .
b1000 /
b1000 0
#80000000
0!
0)
#85000000
1!
b1000 #
1)
b1000 ,
b1000 .
b1001 /
b1001 0
#90000000
0!
0)
#95000000
1!
b1001 #
1)
b1001 ,
b1001 .
b1010 /
b1010 0
#100000000
0!
0)
#105000000
1!
b1010 #
1)
b1010 ,
b1010 .
b1011 /
b1011 0
#110000000
0!
0)
#115000000
1!
b1011 #
1)
b1011 ,
b1011 .
b1100 /
b1100 0
#120000000
0!
0)
#125000000
1!
b1100 #
1)
b1100 ,
b1100 .
b1101 /
b1101 0
#130000000
0!
0)
#135000000
1!
b1101 #
1)
b1101 ,
b1101 .
b1110 /
b1110 0
#140000000
0!
0)
#145000000
1!
b1110 #
1$
1)
b1110 ,
1-
b1110 .
b0000 /
b1111 0
11
#150000000
0!
0)
#155000000
1!
b0000 #
0$
1)
b0000 ,
0-
b0000 .
b0001 /
b0001 0
01
#156000000
b1110 "
b1110 +
#160000000
0!
0)
#165000000
1!
b0001 #
1)
b0001 ,
b0001 .
b0010 /
b0010 0
#170000000
0!
0)
#175000000
1!
b0010 #
1)
b0010 ,
b0010 .
b0011 /
b0011 0
#180000000
0!
0)
#185000000
1!
b0011 #
1)
b0011 ,
b0011 .
b0100 /
b0100 0
#190000000
0!
0)
#195000000
1!
b0100 #
1)
b0100 ,
b0100 .
b0101 /
b0101 0
#200000000
0!
0)
#205000000
1!
b0101 #
1)
b0101 ,
b0101 .
b0110 /
b0110 0
#210000000
0!
0)
#215000000
1!
b0110 #
1)
b0110 ,
b0110 .
b0111 /
b0111 0
#220000000
0!
0)
#225000000
1!
b0111 #
1)
b0111 ,
b0111 .
b1000 /
b1000 0
#230000000
0!
0)
#235000000
1!
b1000 #
1)
b1000 ,
b1000 .
b1001 /
b1001 0
#240000000
0!
0)
#245000000
1!
b1001 #
1)
b1001 ,
b1001 .
b1010 /
b1010 0
#250000000
0!
0)
#255000000
1!
b1010 #
1)
b1010 ,
b1010 .
b1011 /
b1011 0
#260000000
0!
0)
#265000000
1!
b1011 #
1)
b1011 ,
b1011 .
b1100 /
b1100 0
#270000000
0!
0)
#275000000
1!
b1100 #
1)
b1100 ,
b1100 .
b1101 /
b1101 0
#280000000
0!
0)
#285000000
1!
b1101 #
1$
1)
b1101 ,
1-
b1101 .
b0000 /
b1110 0
11
#290000000
0!
0)
#295000000
1!
b0000 #
0$
1)
b0000 ,
0-
b0000 .
b0001 /
b0001 0
01
#296000000
b1000 "
b1000 +
#300000000
0!
0)
#305000000
1!
b0001 #
1)
b0001 ,
b0001 .
b0010 /
b0010 0
#310000000
0!
0)
#315000000
1!
b0010 #
1)
b0010 ,
b0010 .
b0011 /
b0011 0
#320000000
0!
0)
#325000000
1!
b0011 #
1)
b0011 ,
b0011 .
b0100 /
b0100 0
#330000000
0!
0)
#335000000
1!
b0100 #
1)
b0100 ,
b0100 .
b0101 /
b0101 0
#340000000
0!
0)
#345000000
1!
b0101 #
1)
b0101 ,
b0101 .
b0110 /
b0110 0
#350000000
0!
0)
#355000000
1!
b0110 #
1)
b0110 ,
b0110 .
b0111 /
b0111 0
#360000000
0!
0)
#365000000
1!
b0111 #
1$
1)
b0111 ,
1-
b0111 .
b0000 /
b1000 0
11
#370000000
0!
0)
#375000000
1!
b0000 #
0$
1)
b0000 ,
0-
b0000 .
b0001 /
b0001 0
01
#380000000
0!
0)
#385000000
1!
b0001 #
1)
b0001 ,
b0001 .
b0010 /
b0010 0
#390000000
0!
0)
#392000000
0'
0*
