DFFR.vhd
LIBRARY ieee;
USE ieee.std_logic_1164.ALL;
ENTITY DFFR IS
    PORT (
        clk : IN STD_LOGIC;
        reset : IN STD_LOGIC;
        d : IN STD_LOGIC;
        q : OUT STD_LOGIC
    );
END ENTITY;

ARCHITECTURE arch OF DFFR IS
BEGIN
    PROCESS (clk, reset)
    BEGIN
        IF (reset = '1') THEN
            q <= '0';
        ELSIF (clk'event AND clk = '1') THEN
            q <= d;
        END IF;
    END PROCESS;
END ARCHITECTURE;

DFFR_Testbench.vhd
library ieee;
use ieee.std_logic_1164.all;
use ieee.numeric_std.all;
use ieee.math_real.all;
entity DFFR_Testbench is
end DFFR_Testbench;

architecture rtl of DFFR_Testbench is
    component DFFR is
        port (
            clk   : in std_logic;
            reset : in std_logic;
            d : in STD_LOGIC;
            q : out STD_LOGIC
        );
    end component;
    signal clk : std_logic := '0';
    signal reset, success, d, q_expected : std_logic := '1';
    signal q : STD_LOGIC;
begin
    reset <= '1', '0' after 11 ns;
    clk <= not clk after 5 ns; --acts as a clock
    q_expected <= not q_expected after 10 ns;
    d <= not q;
    dut:DFFR
    port map(
        clk => clk,
        reset => reset,
        d => d,
        q => q
    );
    stimulus:
    process begin
        wait until reset = '0';
        if (q /= q_expected) then
            success <= '0';
        end if;
    end process stimulus;

end architecture;

DFFR_Testbench.vcd
$date
  Thu Apr 23 16:11:28 2026
$end
$version
  GHDL v0
$end
$timescale
  1 fs
$end
$scope module standard $end
$upscope $end
$scope module std_logic_1164 $end
$upscope $end
$scope module numeric_std $end
$upscope $end
$scope module math_real $end
$upscope $end
$scope module dffr_testbench $end
$var reg 1 ! clk $end
$var reg 1 " reset $end
$var reg 1 # success $end
$var reg 1 $ d $end
$var reg 1 % q_expected $end
$var reg 1 & q $end
$scope module dut $end
$var reg 1 ' clk $end
$var reg 1 ( reset $end
$var reg 1 ) d $end
$var reg 1 * q $end
$upscope $end
$upscope $end
$enddefinitions $end
#0
0!
1"
1#
1$
1%
0&
0'
1(
1)
0*
#5000000
1!
1'
#10000000
0!
0%
0'
#11000000
0"
0(
#15000000
1!
0$
1&
1'
0)
1*
#20000000
0!
1%
0'
#25000000
1!
1$
0&
1'
1)
0*
#30000000
0!
0%
0'
#35000000
1!
0$
1&
1'
0)
1*
#40000000
0!
1%
0'
#45000000
1!
1$
0&
1'
1)
0*
#50000000
0!
0%
0'
#55000000
1!
0$
1&
1'
0)
1*
#60000000
0!
1%
0'
#65000000
1!
1$
0&
1'
1)
0*
#70000000
0!
0%
0'
#75000000
1!
0$
1&
1'
0)
1*
#80000000
0!
1%
0'
#85000000
1!
1$
0&
1'
1)
0*
#90000000
0!
0%
0'
#95000000
1!
0$
1&
1'
0)
1*
#100000000
0!
1%
0'
#105000000
1!
1$
0&
1'
1)
0*
#110000000
0!
0%
0'
#115000000
1!
0$
1&
1'
0)
1*
#120000000
0!
1%
0'
#125000000
1!
1$
0&
1'
1)
0*
#130000000
0!
0%
0'
#135000000
1!
0$
1&
1'
0)
1*
#140000000
0!
1%
0'
#145000000
1!
1$
0&
1'
1)
0*
#150000000
0!
0%
0'
#155000000
1!
0$
1&
1'
0)
1*
#160000000
0!
1%
0'
#165000000
1!
1$
0&
1'
1)
0*
#170000000
0!
0%
0'
#175000000
1!
0$
1&
1'
0)
1*
#180000000
0!
1%
0'
#185000000
1!
1$
0&
1'
1)
0*
#190000000
0!
0%
0'
#195000000
1!
0$
1&
1'
0)
1*
#200000000
0!
1%
0'
#205000000
1!
1$
0&
1'
1)
0*
#210000000
0!
0%
0'
#215000000
1!
0$
1&
1'
0)
1*
#220000000
0!
1%
0'
#225000000
1!
1$
0&
1'
1)
0*
#230000000
0!
0%
0'
#235000000
1!
0$
1&
1'
0)
1*
#240000000
0!
1%
0'
#245000000
1!
1$
0&
1'
1)
0*
#250000000
0!
0%
0'
#255000000
1!
0$
1&
1'
0)
1*
#260000000
0!
1%
0'
#265000000
1!
1$
0&
1'
1)
0*
#270000000
0!
0%
0'
#275000000
1!
0$
1&
1'
0)
1*
#280000000
0!
1%
0'
#285000000
1!
1$
0&
1'
1)
0*
#290000000
0!
0%
0'
#295000000
1!
0$
1&
1'
0)
1*
#300000000
0!
1%
0'
#305000000
1!
1$
0&
1'
1)
0*
#310000000
0!
0%
0'
#315000000
1!
0$
1&
1'
0)
1*
#320000000
0!
1%
0'
#325000000
1!
1$
0&
1'
1)
0*
#330000000
0!
0%
0'
#335000000
1!
0$
1&
1'
0)
1*
#340000000
0!
1%
0'
#345000000
1!
1$
0&
1'
1)
0*
#350000000
0!
0%
0'
#355000000
1!
0$
1&
1'
0)
1*
#360000000
0!
1%
0'
#365000000
1!
1$
0&
1'
1)
0*
#370000000
0!
0%
0'
#375000000
1!
0$
1&
1'
0)
1*
#380000000
0!
1%
0'
#385000000
1!
1$
0&
1'
1)
0*
#390000000
0!
0%
0'
#395000000
1!
0$
1&
1'
0)
1*
#400000000
0!
1%
0'
#405000000
1!
1$
0&
1'
1)
0*
#410000000
0!
0%
0'
#415000000
1!
0$
1&
1'
0)
1*
#420000000
0!
1%
0'
#425000000
1!
1$
0&
1'
1)
0*
#430000000
0!
0%
0'
#435000000
1!
0$
1&
1'
0)
1*
#440000000
0!
1%
0'
#445000000
1!
1$
0&
1'
1)
0*
#450000000
0!
0%
0'
#455000000
1!
0$
1&
1'
0)
1*
#460000000
0!
1%
0'
#465000000
1!
1$
0&
1'
1)
0*
#470000000
0!
0%
0'
#475000000
1!
0$
1&
1'
0)
1*
#480000000
0!
1%
0'
#485000000
1!
1$
0&
1'
1)
0*
#490000000
0!
0%
0'
#495000000
1!
0$
1&
1'
0)
1*
#500000000
0!
1%
0'
