Counter4bit.vhd
LIBRARY ieee;
USE ieee.std_logic_1164.ALL;
USE ieee.numeric_std.ALL;
ENTITY counter4bit IS
    PORT (
        reset, clk, en : IN STD_LOGIC;
        n : IN STD_LOGIC_VECTOR(3 DOWNTO 0);
        q : OUT STD_LOGIC_VECTOR(3 DOWNTO 0);
        p : OUT STD_LOGIC);
    -- n is the number that the counter will reset at and pulse at.
END ENTITY;

ARCHITECTURE seq OF counter4bit IS
    SIGNAL r_reg, r_next, r_inc : unsigned(3 DOWNTO 0) := (others => '0');
    SIGNAL rollover : BOOLEAN;
BEGIN
    PROCESS (clk, reset, en)
    BEGIN
        IF (reset = '1') THEN
            r_reg <= (OTHERS => '0');
        ELSIF rising_edge(clk) AND en = '1' THEN
            r_reg <= r_next;
        END IF;
    END PROCESS;
    r_inc <= r_reg + "1";
    r_next <= (OTHERS => '0') WHEN rollover ELSE
              r_inc;
    rollover <= r_inc = unsigned(n);
    q <= STD_LOGIC_VECTOR(r_reg);
    p <= '1' WHEN rollover ELSE '0';
    --        PROCESS (rollover, reset)
    --        BEGIN
    --            IF (reset = '1') THEN
    --                p <= '0';
    --            ELSIF rollover THEN
    --                p <= '1';
    --            END IF;
    --        END PROCESS;
END ARCHITECTURE;

DFFR.vhd
LIBRARY ieee;
USE ieee.std_logic_1164.ALL;
ENTITY DFFR IS
    PORT (
        clk : IN STD_LOGIC;
        reset : IN STD_LOGIC;
        d : IN STD_LOGIC;
        q : OUT STD_LOGIC
    );
END ENTITY;

ARCHITECTURE arch OF DFFR IS
BEGIN
    PROCESS (clk, reset)
    BEGIN
        IF (reset = '1') THEN
            q <= '0';
        ELSIF (clk'event AND clk = '1') THEN
            q <= d;
        END IF;
    END PROCESS;
END ARCHITECTURE;

FlashLed.vhd
LIBRARY ieee;
USE ieee.std_logic_1164.ALL;
ENTITY FlashLed IS
    PORT (
        clk, reset, pulse : IN STD_LOGIC;
        LED : OUT STD_LOGIC
    );
END ENTITY;

ARCHITECTURE arch OF FlashLed IS
    COMPONENT DFFR IS
        PORT (
            clk : IN STD_LOGIC;
            reset : IN STD_LOGIC;
            d : IN STD_LOGIC;
            q : OUT STD_LOGIC
        );
    END COMPONENT;
    COMPONENT counter4bit IS
        PORT (
            reset, clk, en : IN STD_LOGIC;
            n : IN STD_LOGIC_VECTOR(3 DOWNTO 0);
            q : OUT STD_LOGIC_VECTOR(3 DOWNTO 0);
            p : OUT STD_LOGIC
        );
    END COMPONENT;
    SIGNAL p, flip, flip2 : STD_LOGIC;
    SIGNAL n, q : STD_LOGIC_VECTOR(3 DOWNTO 0);
BEGIN
    winner : DFFR
    PORT MAP(
        clk => p,
        reset => reset,
        d => flip,
        q => flip2
    );
    flash : counter4bit
    PORT MAP(
        reset => reset,
        clk => clk,
        en => pulse,
        n => n,
        q => q,
        p => p
    );
    flip <= NOT flip2;
    LED <= flip2;
    n <= "1111";
END ARCHITECTURE;

FlashLed_Testbench.vhd
library ieee;
use ieee.std_logic_1164.all;
use ieee.numeric_std.all;
use ieee.math_real.all;
entity FlashLed_Testbench is
end FlashLed_Testbench;

architecture arch of FlashLed_Testbench is
    component FlashLed is
        port (
            clk, reset, pulse: in STD_LOGIC;
            LED : out std_logic
        );
    end component;
    signal clk, pulse, LED : STD_LOGIC := '0';
    signal reset, success : STD_LOGIC := '1';
begin
    reset <= '1', '0' after 11 ns;
    clk <= not clk after 5 ns; --acts as a clock
    dut:FlashLed
    port map(
        clk => clk,
        pulse => pulse,
        reset => reset,
        LED => LED
    );
    stimulus:
    process begin
        wait until reset = '0';
        for i in 0 to 14 loop
            pulse <= '1';
            wait for 10 ns;
            pulse <= '0';
            wait for 10 ns;
        end loop;
        if LED /= '1' then
            success <= '0';
        end if;
        for i in 0 to 14 loop
            pulse <= '1';
            wait for 10 ns;
            pulse <= '0';
            wait for 10 ns;
        end loop;
        if LED /= '0' then
            success <= '0';
        end if;
    end process stimulus;

end arch;

FlashLed_Testbench.vcd
$date
  Thu Apr 23 16:18:09 2026
$end
$version
  GHDL v0
$end
$timescale
  1 fs
$end
$scope module standard $end
$upscope $end
$scope module std_logic_1164 $end
$upscope $end
$scope module numeric_std $end
$upscope $end
$scope module math_real $end
$upscope $end
$scope module flashled_testbench $end
$var reg 1 ! clk $end
$var reg 1 " pulse $end
$var reg 1 # led $end
$var reg 1 $ reset $end
$var reg 1 % success $end
$scope module dut $end
$var reg 1 & clk $end
$var reg 1 ' reset $end
$var reg 1 ( pulse $end
$var reg 1 ) led $end
$var reg 1 * p $end
$var reg 1 + flip $end
$var reg 1 , flip2 $end
$var reg 4 - n[3:0] $end
$var reg 4 . q[3:0] $end
$scope module winner $end
$var reg 1 / clk $end
$var reg 1 0 reset $end
$var reg 1 1 d $end
$var reg 1 2 q $end
$upscope $end
$scope module flash $end
$var reg 1 3 reset $end
$var reg 1 4 clk $end
$var reg 1 5 en $end
$var reg 4 6 n[3:0] $end
$var reg 4 7 q[3:0] $end
$var reg 1 8 p $end
$var reg 4 9 r_reg[3:0] $end
$var reg 4 : r_next[3:0] $end
$var reg 4 ; r_inc[3:0] $end
$var reg 1 < rollover $end
$upscope $end
$upscope $end
$upscope $end
$enddefinitions $end
#0
0!
0"
0#
1$
1%
0&
1'
0(
0)
0*
1+
0,
b1111 -
b0000 .
0/
10
11
02
13
04
05
b1111 6
b0000 7
08
b0000 9
b0001 :
b0001 ;
0<
#5000000
1!
1&
14
#10000000
0!
0&
04
#11000000
1"
0$
0'
1(
00
03
15
#15000000
1!
1&
b0001 .
14
b0001 7
b0001 9
b0010 :
b0010 ;
#20000000
0!
0&
04
#21000000
0"
0(
05
#25000000
1!
1&
14
#30000000
0!
0&
04
#31000000
1"
1(
15
#35000000
1!
1&
b0010 .
14
b0010 7
b0010 9
b0011 :
b0011 ;
#40000000
0!
0&
04
#41000000
0"
0(
05
#45000000
1!
1&
14
#50000000
0!
0&
04
#51000000
1"
1(
15
#55000000
1!
1&
b0011 .
14
b0011 7
b0011 9
b0100 :
b0100 ;
#60000000
0!
0&
04
#61000000
0"
0(
05
#65000000
1!
1&
14
#70000000
0!
0&
04
#71000000
1"
1(
15
#75000000
1!
1&
b0100 .
14
b0100 7
b0100 9
b0101 :
b0101 ;
#80000000
0!
0&
04
#81000000
0"
0(
05
#85000000
1!
1&
14
#90000000
0!
0&
04
#91000000
1"
1(
15
#95000000
1!
1&
b0101 .
14
b0101 7
b0101 9
b0110 :
b0110 ;
#100000000
0!
0&
04
#101000000
0"
0(
05
#105000000
1!
1&
14
#110000000
0!
0&
04
#111000000
1"
1(
15
#115000000
1!
1&
b0110 .
14
b0110 7
b0110 9
b0111 :
b0111 ;
#120000000
0!
0&
04
#121000000
0"
0(
05
#125000000
1!
1&
14
#130000000
0!
0&
04
#131000000
1"
1(
15
#135000000
1!
1&
b0111 .
14
b0111 7
b0111 9
b1000 :
b1000 ;
#140000000
0!
0&
04
#141000000
0"
0(
05
#145000000
1!
1&
14
#150000000
0!
0&
04
#151000000
1"
1(
15
#155000000
1!
1&
b1000 .
14
b1000 7
b1000 9
b1001 :
b1001 ;
#160000000
0!
0&
04
#161000000
0"
0(
05
#165000000
1!
1&
14
#170000000
0!
0&
04
#171000000
1"
1(
15
#175000000
1!
1&
b1001 .
14
b1001 7
b1001 9
b1010 :
b1010 ;
#180000000
0!
0&
04
#181000000
0"
0(
05
#185000000
1!
1&
14
#190000000
0!
0&
04
#191000000
1"
1(
15
#195000000
1!
1&
b1010 .
14
b1010 7
b1010 9
b1011 :
b1011 ;
#200000000
0!
0&
04
#201000000
0"
0(
05
#205000000
1!
1&
14
#210000000
0!
0&
04
#211000000
1"
1(
15
#215000000
1!
1&
b1011 .
14
b1011 7
b1011 9
b1100 :
b1100 ;
#220000000
0!
0&
04
#221000000
0"
0(
05
#225000000
1!
1&
14
#230000000
0!
0&
04
#231000000
1"
1(
15
#235000000
1!
1&
b1100 .
14
b1100 7
b1100 9
b1101 :
b1101 ;
#240000000
0!
0&
04
#241000000
0"
0(
05
#245000000
1!
1&
14
#250000000
0!
0&
04
#251000000
1"
1(
15
#255000000
1!
1&
b1101 .
14
b1101 7
b1101 9
b1110 :
b1110 ;
#260000000
0!
0&
04
#261000000
0"
0(
05
#265000000
1!
1&
14
#270000000
0!
0&
04
#271000000
1"
1(
15
#275000000
1!
1#
1&
1)
1*
0+
1,
b1110 .
1/
01
12
14
b1110 7
18
b1110 9
b0000 :
b1111 ;
1<
#280000000
0!
0&
04
#281000000
0"
0(
05
#285000000
1!
1&
14
#290000000
0!
0&
04
#291000000
1"
1(
15
#295000000
1!
1&
0*
b0000 .
0/
14
b0000 7
08
b0000 9
b0001 :
b0001 ;
0<
#300000000
0!
0&
04
#301000000
0"
0(
05
#305000000
1!
1&
14
#310000000
0!
0&
04
#311000000
1"
1(
15
#315000000
1!
1&
b0001 .
14
b0001 7
b0001 9
b0010 :
b0010 ;
#320000000
0!
0&
04
#321000000
0"
0(
05
#325000000
1!
1&
14
#330000000
0!
0&
04
#331000000
1"
1(
15
#335000000
1!
1&
b0010 .
14
b0010 7
b0010 9
b0011 :
b0011 ;
#340000000
0!
0&
04
#341000000
0"
0(
05
#345000000
1!
1&
14
#350000000
0!
0&
04
#351000000
1"
1(
15
#355000000
1!
1&
b0011 .
14
b0011 7
b0011 9
b0100 :
b0100 ;
#360000000
0!
0&
04
#361000000
0"
0(
05
#365000000
1!
1&
14
#370000000
0!
0&
04
#371000000
1"
1(
15
#375000000
1!
1&
b0100 .
14
b0100 7
b0100 9
b0101 :
b0101 ;
#380000000
0!
0&
04
#381000000
0"
0(
05
#385000000
1!
1&
14
#390000000
0!
0&
04
#391000000
1"
1(
15
#395000000
1!
1&
b0101 .
14
b0101 7
b0101 9
b0110 :
b0110 ;
#400000000
0!
0&
04
#401000000
0"
0(
05
#405000000
1!
1&
14
#410000000
0!
0&
04
#411000000
1"
1(
15
#415000000
1!
1&
b0110 .
14
b0110 7
b0110 9
b0111 :
b0111 ;
#420000000
0!
0&
04
#421000000
0"
0(
05
#425000000
1!
1&
14
#430000000
0!
0&
04
#431000000
1"
1(
15
#435000000
1!
1&
b0111 .
14
b0111 7
b0111 9
b1000 :
b1000 ;
#440000000
0!
0&
04
#441000000
0"
0(
05
#445000000
1!
1&
14
#450000000
0!
0&
04
#451000000
1"
1(
15
#455000000
1!
1&
b1000 .
14
b1000 7
b1000 9
b1001 :
b1001 ;
#460000000
0!
0&
04
#461000000
0"
0(
05
#465000000
1!
1&
14
#470000000
0!
0&
04
#471000000
1"
1(
15
#475000000
1!
1&
b1001 .
14
b1001 7
b1001 9
b1010 :
b1010 ;
#480000000
0!
0&
04
#481000000
0"
0(
05
#485000000
1!
1&
14
#490000000
0!
0&
04
#491000000
1"
1(
15
#495000000
1!
1&
b1010 .
14
b1010 7
b1010 9
b1011 :
b1011 ;
#500000000
0!
0&
04
#501000000
0"
0(
05
#505000000
1!
1&
14
#510000000
0!
0&
04
#511000000
1"
1(
15
#515000000
1!
1&
b1011 .
14
b1011 7
b1011 9
b1100 :
b1100 ;
#520000000
0!
0&
04
#521000000
0"
0(
05
#525000000
1!
1&
14
#530000000
0!
0&
04
#531000000
1"
1(
15
#535000000
1!
1&
b1100 .
14
b1100 7
b1100 9
b1101 :
b1101 ;
#540000000
0!
0&
04
#541000000
0"
0(
05
#545000000
1!
1&
14
#550000000
0!
0&
04
#551000000
1"
1(
15
#555000000
1!
1&
b1101 .
14
b1101 7
b1101 9
b1110 :
b1110 ;
#560000000
0!
0&
04
#561000000
0"
0(
05
#565000000
1!
1&
14
#570000000
0!
0&
04
#571000000
1"
1(
15
#575000000
1!
0#
1&
0)
1*
1+
0,
b1110 .
1/
11
02
14
b1110 7
18
b1110 9
b0000 :
b1111 ;
1<
#580000000
0!
0&
04
#581000000
0"
0(
05
#585000000
1!
1&
14
#590000000
0!
0&
04
#591000000
1"
1(
15
#595000000
1!
1&
0*
b0000 .
0/
14
b0000 7
08
b0000 9
b0001 :
b0001 ;
0<
