hextoFourDigit.vhd
-- This code used to be only about the part to the right of the decimal point
-- But instead of just making a new code to do the left side, I just added it to this

LIBRARY ieee;
USE ieee.std_logic_1164.ALL;
ENTITY hextoFourDigit IS
    PORT (
        i0 : IN STD_LOGIC_VECTOR(7 DOWNTO 0);
        left, right, o0, o1, o2, o3 : OUT STD_LOGIC_VECTOR(3 DOWNTO 0)
    );
END ENTITY;

ARCHITECTURE arch OF hextoFourDigit IS
BEGIN
    WITH i0(7 DOWNTO 4) SELECT
    left <= "0000" WHEN "0000" | "0001" | "0010" | "0011" | "0100" | "0101" | "0110" | "0111" | "1000" | "1001",
            "0001" WHEN OTHERS;
    WITH i0(7 DOWNTO 4) SELECT
    right <= "0000" WHEN "0000" | "1010",
             "0001" WHEN "0001" | "1011",
             "0010" WHEN "0010" | "1100",
             "0011" WHEN "0011" | "1101",
             "0100" WHEN "0100" | "1110",
             "0101" WHEN "0101" | "1111",
             "0110" WHEN "0110",
             "0111" WHEN "0111",
             "1000" WHEN "1000",
             "1001" WHEN OTHERS;
    WITH i0(3 DOWNTO 0) SELECT --increments of 0.0625
    o0 <= "0000" WHEN "0000" | "0001",
          "0001" WHEN "0010" | "0011",
          "0010" WHEN "0100",
          "0011" WHEN "0101" | "0110",
          "0100" WHEN "0111",
          "0101" WHEN "1000" | "1001",
          "0110" WHEN "1010" | "1011",
          "0111" WHEN "1100",
          "1000" WHEN "1101" | "1110",
          "1001" WHEN OTHERS;
    WITH i0(2 DOWNTO 0) SELECT
    o1 <= "0000" WHEN "000",
          "0001" WHEN "101",
          "0010" WHEN "010",
          "0011" WHEN "111",
          "0101" WHEN "100",
          "0110" WHEN "001",
          "0111" WHEN "110",
          "1000" WHEN OTHERS;
    WITH i0(1 DOWNTO 0) SELECT
    o2 <= "0000" WHEN "00",
          "0010" WHEN "01",
          "0101" WHEN "10",
          "0111" WHEN OTHERS;
    WITH i0(0) SELECT
    o3 <= "0000" WHEN '0',
          "0101" WHEN OTHERS;
END ARCHITECTURE;

hexDecoderTestbench.vhd
library ieee;
use ieee.std_logic_1164.all;
use ieee.numeric_std.all;
use ieee.math_real.all;
entity hexDecoderTestbench is
end hexDecoderTestbench;

architecture arch of hexDecoderTestbench is
    component hextoFourDigit is
        port (
            i0 : in STD_LOGIC_VECTOR(7 downto 0);
            left, right, o0, o1, o2, o3 : out STD_LOGIC_VECTOR(3 downto 0)
        );
    end component;
    signal reset, success : std_logic := '1';
    signal i0 : STD_LOGIC_VECTOR(7 downto 0) := "00000000";
    signal left, right, o0, o1, o2, o3 : STD_LOGIC_VECTOR(3 downto 0) := "0000";
begin
    reset <= '1', '0' after 5 ns;
    dut:hextoFourDigit
    port map(
        i0 => i0,
        left => left,
        right => right,
        o0 => o0,
        o1 => o1,
        o2 => o2,
        o3 => o3
    );
    stimulus:
    process begin
        wait until reset = '0';
        i0(7 downto 4) <= "0000";
        wait for 2 ns;
        if (left /= "0000") and (right /= "0000") then
            success <= '0';
        end if;
        i0(7 downto 4) <= "0001";
        wait for 2 ns;
        if (left /= "0000") and (right /= "0001") then
            success <= '0';
        end if;
        i0(7 downto 4) <= "0010";
        wait for 2 ns;
        if (left /= "0000") and (right /= "0010") then
            success <= '0';
        end if;
        i0(7 downto 4) <= "0011";
        wait for 2 ns;
        if (left /= "0000") and (right /= "0011") then
            success <= '0';
        end if;
        i0(7 downto 4) <= "0100";
        wait for 2 ns;
        if (left /= "0000") and (right /= "0100") then
            success <= '0';
        end if;
        i0(7 downto 4) <= "0101";
        wait for 2 ns;
        if (left /= "0000") and (right /= "0101") then
            success <= '0';
        end if;
        i0(7 downto 4) <= "0110";
        wait for 2 ns;
        if (left /= "0000") and (right /= "0110") then
            success <= '0';
        end if;
        i0(7 downto 4) <= "0111";
        wait for 2 ns;
        if (left /= "0000") and (right /= "0111") then
            success <= '0';
        end if;
        i0(7 downto 4) <= "1000";
        wait for 2 ns;
        if (left /= "0000") and (right /= "1000") then
            success <= '0';
        end if;
        i0(7 downto 4) <= "1001";
        wait for 2 ns;
        if (left /= "0000") and (right /= "1001") then
            success <= '0';
        end if;
        i0(7 downto 4) <= "1010";
        wait for 2 ns;
        if (left /= "0001") and (right /= "0000") then
            success <= '0';
        end if;
        i0(7 downto 4) <= "1011";
        wait for 2 ns;
        if (left /= "0001") and (right /= "0001") then
            success <= '0';
        end if;
        i0(7 downto 4) <= "1100";
        wait for 2 ns;
        if (left /= "0001") and (right /= "0010") then
            success <= '0';
        end if;
        i0(7 downto 4) <= "1101";
        wait for 2 ns;
        if (left /= "0001") and (right /= "0011") then
            success <= '0';
        end if;
        i0(7 downto 4) <= "1110";
        wait for 2 ns;
        if (left /= "0001") and (right /= "0100") then
            success <= '0';
        end if;
        i0(7 downto 4) <= "1111";
        wait for 2 ns;
        if (left /= "0001") and (right /= "0101") then
            success <= '0';
        end if;
        i0(7 downto 4) <= "0000";
        i0(3 downto 0) <= "0000";
        wait for 2 ns;
        if (o0 /= "0000") and (o1 /= "0000") and (o2 /= "0000") and (o3 /= "0000") then
            success <= '0';
        end if;
        i0(3 downto 0) <= "0001";
        wait for 2 ns;
        if (o0 /= "0000") and (o1 /= "0110") and (o2 /= "0010") and (o3 /= "0101") then
            success <= '0';
        end if;
        i0(3 downto 0) <= "0010";
        wait for 2 ns;
        if (o0 /= "0001") and (o1 /= "0010") and (o2 /= "0101") and (o3 /= "0000") then
            success <= '0';
        end if;
        i0(3 downto 0) <= "0011";
        wait for 2 ns;
        if (o0 /= "0001") and (o1 /= "1000") and (o2 /= "0111") and (o3 /= "0101") then
            success <= '0';
        end if;
        i0(3 downto 0) <= "0100";
        wait for 2 ns;
        if (o0 /= "0010") and (o1 /= "0101") and (o2 /= "0000") and (o3 /= "0000") then
            success <= '0';
        end if;
        i0(3 downto 0) <= "0101";
        wait for 2 ns;
        if (o0 /= "0011") and (o1 /= "0001") and (o2 /= "0010") and (o3 /= "0101") then
            success <= '0';
        end if;
        i0(3 downto 0) <= "0110";
        wait for 2 ns;
        if (o0 /= "0011") and (o1 /= "0111") and (o2 /= "0101") and (o3 /= "0000") then
            success <= '0';
        end if;
        i0(3 downto 0) <= "0111";
        wait for 2 ns;
        if (o0 /= "0100") and (o1 /= "0011") and (o2 /= "0111") and (o3 /= "0101") then
            success <= '0';
        end if;
        i0(3 downto 0) <= "1000";
        wait for 2 ns;
        if (o0 /= "0101") and (o1 /= "0000") and (o2 /= "0000") and (o3 /= "0000") then
            success <= '0';
        end if;
        i0(3 downto 0) <= "1001";
        wait for 2 ns;
        if (o0 /= "0101") and (o1 /= "0110") and (o2 /= "0010") and (o3 /= "0101") then
            success <= '0';
        end if;
        i0(3 downto 0) <= "1010";
        wait for 2 ns;
        if (o0 /= "0110") and (o1 /= "0010") and (o2 /= "0101") and (o3 /= "0000") then
            success <= '0';
        end if;
        i0(3 downto 0) <= "1011";
        wait for 2 ns;
        if (o0 /= "0110") and (o1 /= "1000") and (o2 /= "0111") and (o3 /= "0101") then
            success <= '0';
        end if;
        i0(3 downto 0) <= "1100";
        wait for 2 ns;
        if (o0 /= "0111") and (o1 /= "0101") and (o2 /= "0000") and (o3 /= "0000") then
            success <= '0';
        end if;
        i0(3 downto 0) <= "1101";
        wait for 2 ns;
        if (o0 /= "1000") and (o1 /= "0001") and (o2 /= "0010") and (o3 /= "0101") then
            success <= '0';
        end if;
        i0(3 downto 0) <= "1110";
        wait for 2 ns;
        if (o0 /= "1000") and (o1 /= "0111") and (o2 /= "0101") and (o3 /= "0000") then
            success <= '0';
        end if;
        i0(3 downto 0) <= "1111";
        wait for 2 ns;
        if (o0 /= "1001") and (o1 /= "0011") and (o2 /= "0111") and (o3 /= "0101") then
            success <= '0';
        end if;
        wait;
    end process stimulus;
end arch;

hexDecoderTestbench.vcd
$date
  Thu Apr 23 16:30:37 2026
$end
$version
  GHDL v0
$end
$timescale
  1 fs
$end
$scope module standard $end
$upscope $end
$scope module std_logic_1164 $end
$upscope $end
$scope module numeric_std $end
$upscope $end
$scope module math_real $end
$upscope $end
$scope module hexdecodertestbench $end
$var reg 1 ! reset $end
$var reg 1 " success $end
$var reg 8 # i0[7:0] $end
$var reg 4 $ left[3:0] $end
$var reg 4 % right[3:0] $end
$var reg 4 & o0[3:0] $end
$var reg 4 ' o1[3:0] $end
$var reg 4 ( o2[3:0] $end
$var reg 4 ) o3[3:0] $end
$scope module dut $end
$var reg 8 * i0[7:0] $end
$var reg 4 + left[3:0] $end
$var reg 4 , right[3:0] $end
$var reg 4 - o0[3:0] $end
$var reg 4 . o1[3:0] $end
$var reg 4 / o2[3:0] $end
$var reg 4 0 o3[3:0] $end
$upscope $end
$upscope $end
$enddefinitions $end
#0
1!
1"
b00000000 #
b0000 $
b0000 %
b0000 &
b0000 '
b0000 (
b0000 )
b00000000 *
b0000 +
b0000 ,
b0000 -
b0000 .
b0000 /
b0000 0
#5000000
0!
#7000000
b00010000 #
b0001 %
b00010000 *
b0001 ,
#9000000
b00100000 #
b0010 %
b00100000 *
b0010 ,
#11000000
b00110000 #
b0011 %
b00110000 *
b0011 ,
#13000000
b01000000 #
b0100 %
b01000000 *
b0100 ,
#15000000
b01010000 #
b0101 %
b01010000 *
b0101 ,
#17000000
b01100000 #
b0110 %
b01100000 *
b0110 ,
#19000000
b01110000 #
b0111 %
b01110000 *
b0111 ,
#21000000
b10000000 #
b1000 %
b10000000 *
b1000 ,
#23000000
b10010000 #
b1001 %
b10010000 *
b1001 ,
#25000000
b10100000 #
b0001 $
b0000 %
b10100000 *
b0001 +
b0000 ,
#27000000
b10110000 #
b0001 %
b10110000 *
b0001 ,
#29000000
b11000000 #
b0010 %
b11000000 *
b0010 ,
#31000000
b11010000 #
b0011 %
b11010000 *
b0011 ,
#33000000
b11100000 #
b0100 %
b11100000 *
b0100 ,
#35000000
b11110000 #
b0101 %
b11110000 *
b0101 ,
#37000000
b00000000 #
b0000 $
b0000 %
b00000000 *
b0000 +
b0000 ,
#39000000
b00000001 #
b0110 '
b0010 (
b0101 )
b00000001 *
b0110 .
b0010 /
b0101 0
#41000000
b00000010 #
b0001 &
b0010 '
b0101 (
b0000 )
b00000010 *
b0001 -
b0010 .
b0101 /
b0000 0
#43000000
b00000011 #
b1000 '
b0111 (
b0101 )
b00000011 *
b1000 .
b0111 /
b0101 0
#45000000
b00000100 #
b0010 &
b0101 '
b0000 (
b0000 )
b00000100 *
b0010 -
b0101 .
b0000 /
b0000 0
#47000000
b00000101 #
b0011 &
b0001 '
b0010 (
b0101 )
b00000101 *
b0011 -
b0001 .
b0010 /
b0101 0
#49000000
b00000110 #
b0111 '
b0101 (
b0000 )
b00000110 *
b0111 .
b0101 /
b0000 0
#51000000
b00000111 #
b0100 &
b0011 '
b0111 (
b0101 )
b00000111 *
b0100 -
b0011 .
b0111 /
b0101 0
#53000000
b00001000 #
b0101 &
b0000 '
b0000 (
b0000 )
b00001000 *
b0101 -
b0000 .
b0000 /
b0000 0
#55000000
b00001001 #
b0110 '
b0010 (
b0101 )
b00001001 *
b0110 .
b0010 /
b0101 0
#57000000
b00001010 #
b0110 &
b0010 '
b0101 (
b0000 )
b00001010 *
b0110 -
b0010 .
b0101 /
b0000 0
#59000000
b00001011 #
b1000 '
b0111 (
b0101 )
b00001011 *
b1000 .
b0111 /
b0101 0
#61000000
b00001100 #
b0111 &
b0101 '
b0000 (
b0000 )
b00001100 *
b0111 -
b0101 .
b0000 /
b0000 0
#63000000
b00001101 #
b1000 &
b0001 '
b0010 (
b0101 )
b00001101 *
b1000 -
b0001 .
b0010 /
b0101 0
#65000000
b00001110 #
b0111 '
b0101 (
b0000 )
b00001110 *
b0111 .
b0101 /
b0000 0
#67000000
b00001111 #
b1001 &
b0011 '
b0111 (
b0101 )
b00001111 *
b1001 -
b0011 .
b0111 /
b0101 0
