IterationHandler_V2.vhd
LIBRARY ieee;
USE ieee.std_logic_1164.ALL;
USE ieee.numeric_std.ALL;
ENTITY IterationHandler_v2 IS
    PORT (
        clk, goNext, reset : IN STD_LOGIC;
        timer : OUT STD_LOGIC_VECTOR(11 DOWNTO 0);
        final : OUT STD_LOGIC);
    -- Next tells the sequence handler to go to next
END ENTITY;

ARCHITECTURE arch OF IterationHandler_v2 IS

    TYPE Iteration_state IS (First, Second, Third, Fourth, Fifth, Sixth, Seventh, Eighth, Ninth, Tenth);
    SIGNAL state_reg, state_next : Iteration_state;
BEGIN
    -- Steps
    PROCESS (clk, reset, state_next)
    BEGIN
        if rising_edge(clk) then
            if reset = '1' then
                state_reg <= First;
            else
                state_reg <= state_next;
            end if;
        END IF;
    END PROCESS;
    -- transitions
    PROCESS (state_reg, goNext)
    BEGIN
        CASE state_reg IS
            WHEN First =>
                IF goNext = '1' THEN
                    state_next <= Second;
                else
                    state_next <= First;
                END IF;
            WHEN Second =>
                IF goNext = '1' THEN
                    state_next <= Third;
                else
                    state_next <= Second;
                END IF;
            WHEN Third =>
                IF goNext = '1' THEN
                    state_next <= Fourth;
                else
                    state_next <= Third;
                END IF;
            WHEN Fourth =>
                IF goNext = '1' THEN
                    state_next <= Fifth;
                else
                    state_next <= Fourth;
                END IF;
            WHEN Fifth =>
                IF goNext = '1' THEN
                    state_next <= Sixth;
                else
                    state_next <= Fifth;
                END IF;
            WHEN Sixth =>
                IF goNext = '1' THEN
                    state_next <= Seventh;
                else
                    state_next <= Sixth;
                END IF;
            WHEN Seventh =>
                IF goNext = '1' THEN
                    state_next <= Eighth;
                else
                    state_next <= Seventh;
                END IF;
            WHEN Eighth =>
                IF goNext = '1' THEN
                    state_next <= Ninth;
                else
                    state_next <= Eighth;
                END IF;
            WHEN Ninth =>
                IF goNext = '1' THEN
                    state_next <= Tenth;
                else
                    state_next <= Ninth;
                END IF;
            WHEN Tenth =>
                state_next <= Tenth;
        END CASE;
    END PROCESS;
    -- actions
    PROCESS (State_reg)
    BEGIN
        timer <= (OTHERS => '0');
        final <= '0';
        CASE state_reg IS
            WHEN First =>
                timer <= "011000000000"; -- 6s
            WHEN Second =>
                timer <= "010010000000"; -- 4.5s
            WHEN Third =>
                timer <= "001101100000"; -- 3.375s
            WHEN Fourth =>
                timer <= "001010001000"; -- 2.53125s
            WHEN Fifth =>
                timer <= "000111100110"; -- 1.8984375s
            WHEN Sixth =>
                timer <= "000101101100"; -- 1.421875s
            WHEN Seventh =>
                timer <= "000100010001"; -- 1.06640625s
            WHEN Eighth =>
                timer <= "000011001101"; -- 0.80078125s
            WHEN Ninth =>
                timer <= "000010011001"; -- 0.59765625s
            WHEN Tenth =>
                timer <= "000001110011"; -- 0.44921875s
                final <= '1';
        END CASE;
    END PROCESS;
END ARCHITECTURE;

IterationHandler_Testbench.vhd
library ieee;
use ieee.std_logic_1164.all;
use ieee.numeric_std.all;
use ieee.math_real.all;
entity IterationHandler_Testbench is
end entity;

architecture arch of IterationHandler_Testbench is
    component IterationHandler_v2 is
        port (
            clk, goNext, reset : IN STD_LOGIC;
            timer : OUT STD_LOGIC_VECTOR(11 DOWNTO 0);
            final : OUT STD_LOGIC
        );
    end component;
    signal goNext, final, clk : STD_LOGIC := '0';
    signal reset, success : STD_LOGIC := '1';
    signal timer : STD_LOGIC_VECTOR(11 downto 0) := (others => '0');
begin
    clk <= not clk after 5 ns;
    goNext <= not goNext after 10 ns;
    dut:IterationHandler_v2
    port map(
        goNext => goNext,
        reset => reset,
        timer => timer,
        final => final,
        clk => clk
    );
    stimulus:
    process begin
        reset <= '1';
        wait for 7 ns;
        reset <= '0';
        wait for 180 ns;
        if final /= '1' then
            success <= '0';
        end if;
        wait for 3 ns;
        reset <= '1';
        wait for 7 ns;
        reset <= '0';
        wait;
    end process stimulus;
end arch;

IterationHandler_Testbench.vcd
$date
  Thu Apr 23 16:32:57 2026
$end
$version
  GHDL v0
$end
$timescale
  1 fs
$end
$scope module standard $end
$upscope $end
$scope module std_logic_1164 $end
$upscope $end
$scope module numeric_std $end
$upscope $end
$scope module math_real $end
$upscope $end
$scope module iterationhandler_testbench $end
$var reg 1 ! gonext $end
$var reg 1 " final $end
$var reg 1 # clk $end
$var reg 1 $ reset $end
$var reg 1 % success $end
$var reg 12 & timer[11:0] $end
$scope module dut $end
$var reg 1 ' clk $end
$var reg 1 ( gonext $end
$var reg 1 ) reset $end
$var reg 12 * timer[11:0] $end
$var reg 1 + final $end
$comment state_reg is not handled $end
$comment state_next is not handled $end
$upscope $end
$upscope $end
$enddefinitions $end
#0
0!
0"
0#
1$
1%
b011000000000 &
0'
0(
1)
b011000000000 *
0+
#5000000
1#
1'
#7000000
0$
0)
#10000000
1!
0#
0'
1(
#15000000
1#
b010010000000 &
1'
b010010000000 *
#20000000
0!
0#
0'
0(
#25000000
1#
1'
#30000000
1!
0#
0'
1(
#35000000
1#
b001101100000 &
1'
b001101100000 *
#40000000
0!
0#
0'
0(
#45000000
1#
1'
#50000000
1!
0#
0'
1(
#55000000
1#
b001010001000 &
1'
b001010001000 *
#60000000
0!
0#
0'
0(
#65000000
1#
1'
#70000000
1!
0#
0'
1(
#75000000
1#
b000111100110 &
1'
b000111100110 *
#80000000
0!
0#
0'
0(
#85000000
1#
1'
#90000000
1!
0#
0'
1(
#95000000
1#
b000101101100 &
1'
b000101101100 *
#100000000
0!
0#
0'
0(
#105000000
1#
1'
#110000000
1!
0#
0'
1(
#115000000
1#
b000100010001 &
1'
b000100010001 *
#120000000
0!
0#
0'
0(
#125000000
1#
1'
#130000000
1!
0#
0'
1(
#135000000
1#
b000011001101 &
1'
b000011001101 *
#140000000
0!
0#
0'
0(
#145000000
1#
1'
#150000000
1!
0#
0'
1(
#155000000
1#
b000010011001 &
1'
b000010011001 *
#160000000
0!
0#
0'
0(
#165000000
1#
1'
#170000000
1!
0#
0'
1(
#175000000
1"
1#
b000001110011 &
1'
b000001110011 *
1+
#180000000
0!
0#
0'
0(
#185000000
1#
1'
#190000000
1!
0#
1$
0'
1(
1)
#195000000
0"
1#
b011000000000 &
1'
b011000000000 *
0+
#197000000
0$
0)
#200000000
0!
0#
0'
0(
#205000000
1#
1'
#210000000
1!
0#
0'
1(
#215000000
1#
b010010000000 &
1'
b010010000000 *
#220000000
0!
0#
0'
0(
#225000000
1#
1'
#230000000
1!
0#
0'
1(
#235000000
1#
b001101100000 &
1'
b001101100000 *
#240000000
0!
0#
0'
0(
#245000000
1#
1'
#250000000
1!
0#
0'
1(
#255000000
1#
b001010001000 &
1'
b001010001000 *
#260000000
0!
0#
0'
0(
#265000000
1#
1'
#270000000
1!
0#
0'
1(
#275000000
1#
b000111100110 &
1'
b000111100110 *
#280000000
0!
0#
0'
0(
#285000000
1#
1'
#290000000
1!
0#
0'
1(
#295000000
1#
b000101101100 &
1'
b000101101100 *
#300000000
0!
0#
0'
0(
#305000000
1#
1'
#310000000
1!
0#
0'
1(
#315000000
1#
b000100010001 &
1'
b000100010001 *
#320000000
0!
0#
0'
0(
#325000000
1#
1'
#330000000
1!
0#
0'
1(
#335000000
1#
b000011001101 &
1'
b000011001101 *
#340000000
0!
0#
0'
0(
#345000000
1#
1'
#350000000
1!
0#
0'
1(
#355000000
1#
b000010011001 &
1'
b000010011001 *
#360000000
0!
0#
0'
0(
#365000000
1#
1'
#370000000
1!
0#
0'
1(
#375000000
1"
1#
b000001110011 &
1'
b000001110011 *
1+
#380000000
0!
0#
0'
0(
#385000000
1#
1'
#390000000
1!
0#
0'
1(
#395000000
1#
1'
#400000000
0!
0#
0'
0(
#405000000
1#
1'
#410000000
1!
0#
0'
1(
#415000000
1#
1'
#420000000
0!
0#
0'
0(
#425000000
1#
1'
#430000000
1!
0#
0'
1(
#435000000
1#
1'
#440000000
0!
0#
0'
0(
#445000000
1#
1'
#450000000
1!
0#
0'
1(
#455000000
1#
1'
#460000000
0!
0#
0'
0(
#465000000
1#
1'
#470000000
1!
0#
0'
1(
#475000000
1#
1'
#480000000
0!
0#
0'
0(
#485000000
1#
1'
#490000000
1!
0#
0'
1(
#495000000
1#
1'
#500000000
0!
0#
0'
0(
